bdc_connect_sdk/__init__.py
bdc_connect_sdk/auth/__init__.py
bdc_connect_sdk/auth/bdc_connect_client.py
bdc_connect_sdk/auth/databricks_client.py
bdc_connect_sdk/auth/partner_client.py
bdc_connect_sdk/generated/__init__.py
bdc_connect_sdk/generated/api_client.py
bdc_connect_sdk/generated/api_response.py
bdc_connect_sdk/generated/configuration.py
bdc_connect_sdk/generated/exceptions.py
bdc_connect_sdk/generated/rest.py
bdc_connect_sdk/generated/api/__init__.py
bdc_connect_sdk/generated/api/publish_api.py
bdc_connect_sdk/generated/models/__init__.py
bdc_connect_sdk/generated/models/general_response.py
bdc_connect_sdk/generated/models/object_info.py
bdc_connect_sdk/generated/models/put_share_response.py
bdc_connect_sdk/models/certificate_information.py
bdc_connect_sdk/utils/certificate_manager.py
bdc_connect_sdk/utils/csn_generator.py
bdc_connect_sdk/utils/warnings.py
sap_bdc_connect_sdk-1.1.6.dist-info/licenses/LICENSE
test/__init__.py
test/test_bdc_connect_client.py
sap_bdc_connect_sdk-1.1.6.dist-info/METADATA
sap_bdc_connect_sdk-1.1.6.dist-info/WHEEL
sap_bdc_connect_sdk-1.1.6.dist-info/top_level.txt
sap_bdc_connect_sdk-1.1.6.dist-info/RECORD
