Metadata-Version: 2.4
Name: sap-bdc-connect-sdk
Version: 1.1.6
Summary: Python SDK for SAP Business Data Cloud
Home-page: https://www.sap.com
Author: SAP SE
License: SAP DEVELOPER LICENSE AGREEMENT
Keywords: SAP SAPBusinessDataCloud SAPBDC SAPBDCConnect
Classifier: Development Status :: 5 - Production/Stable
Classifier: Programming Language :: Python :: 3
Classifier: Intended Audience :: Developers
Classifier: License :: Other/Proprietary License
Classifier: Operating System :: OS Independent
Requires-Python: >=3.9
License-File: LICENSE
Requires-Dist: typing_extensions<=4.12.0
Requires-Dist: urllib3>=2.6
Requires-Dist: pydantic<=2.10.6,>2.0
Requires-Dist: argparse~=1.4.0
Requires-Dist: python-dateutil<=2.9.0
Requires-Dist: requests<=2.32.0
Requires-Dist: cryptography>=41.0.3
Requires-Dist: protobuf<=5.29.5
Requires-Dist: grpcio-status>=1.62.3
Requires-Dist: PyJWT>=2.10.0
Provides-Extra: test
Requires-Dist: pytest>=4.6.7; extra == "test"
Requires-Dist: pytest-cov>=2.8.1; extra == "test"
Requires-Dist: pytest-randomly==3.15.0; extra == "test"
Dynamic: license-file
Dynamic: provides-extra
Dynamic: requires-dist
